spdx/__init__.py
spdx/data/0BSD.txt
spdx/data/AAL.txt
spdx/data/ADSL.txt
spdx/data/AFL-1.1.txt
spdx/data/AFL-1.2.txt
spdx/data/AFL-2.0.txt
spdx/data/AFL-2.1.txt
spdx/data/AFL-3.0.txt
spdx/data/AGPL-1.0.txt
spdx/data/AGPL-3.0.txt
spdx/data/AMDPLPA.txt
spdx/data/AML.txt
spdx/data/AMPAS.txt
spdx/data/ANTLR-PD.txt
spdx/data/APAFML.txt
spdx/data/APL-1.0.txt
spdx/data/APSL-1.0.txt
spdx/data/APSL-1.1.txt
spdx/data/APSL-1.2.txt
spdx/data/APSL-2.0.txt
spdx/data/Abstyles.txt
spdx/data/Adobe-2006.txt
spdx/data/Adobe-Glyph.txt
spdx/data/Afmparse.txt
spdx/data/Aladdin.txt
spdx/data/Apache-1.0.txt
spdx/data/Apache-1.1.txt
spdx/data/Apache-2.0.txt
spdx/data/Artistic-1.0-Perl.txt
spdx/data/Artistic-1.0-cl8.txt
spdx/data/Artistic-1.0.txt
spdx/data/Artistic-2.0.txt
spdx/data/BSD-2-Clause-FreeBSD.txt
spdx/data/BSD-2-Clause-NetBSD.txt
spdx/data/BSD-2-Clause.txt
spdx/data/BSD-3-Clause-Attribution.txt
spdx/data/BSD-3-Clause-Clear.txt
spdx/data/BSD-3-Clause-LBNL.txt
spdx/data/BSD-3-Clause-No-Nuclear-License-2014.txt
spdx/data/BSD-3-Clause-No-Nuclear-License.txt
spdx/data/BSD-3-Clause-No-Nuclear-Warranty.txt
spdx/data/BSD-3-Clause.txt
spdx/data/BSD-4-Clause-UC.txt
spdx/data/BSD-4-Clause.txt
spdx/data/BSD-Protection.txt
spdx/data/BSD-Source-Code.txt
spdx/data/BSL-1.0.txt
spdx/data/Bahyph.txt
spdx/data/Barr.txt
spdx/data/Beerware.txt
spdx/data/BitTorrent-1.0.txt
spdx/data/BitTorrent-1.1.txt
spdx/data/Borceux.txt
spdx/data/CATOSL-1.1.txt
spdx/data/CC-BY-1.0.txt
spdx/data/CC-BY-2.0.txt
spdx/data/CC-BY-2.5.txt
spdx/data/CC-BY-3.0.txt
spdx/data/CC-BY-4.0.txt
spdx/data/CC-BY-NC-1.0.txt
spdx/data/CC-BY-NC-2.0.txt
spdx/data/CC-BY-NC-2.5.txt
spdx/data/CC-BY-NC-3.0.txt
spdx/data/CC-BY-NC-4.0.txt
spdx/data/CC-BY-NC-ND-1.0.txt
spdx/data/CC-BY-NC-ND-2.0.txt
spdx/data/CC-BY-NC-ND-2.5.txt
spdx/data/CC-BY-NC-ND-3.0.txt
spdx/data/CC-BY-NC-ND-4.0.txt
spdx/data/CC-BY-NC-SA-1.0.txt
spdx/data/CC-BY-NC-SA-2.0.txt
spdx/data/CC-BY-NC-SA-2.5.txt
spdx/data/CC-BY-NC-SA-3.0.txt
spdx/data/CC-BY-NC-SA-4.0.txt
spdx-2.5.1.dist-info/LICENSE
spdx-2.5.1.dist-info/METADATA
spdx-2.5.1.dist-info/WHEEL
spdx-2.5.1.dist-info/top_level.txt
spdx-2.5.1.dist-info/RECORD
