Metadata-Version: 2.1
Name: spdx
Version: 2.5.1
Summary: SPDX license list database
Home-page: https://github.com/bbqsrc/spdx-python
Author: Brendan Molloy
Author-email: brendan+pypi@bbqsrc.net
License: CC0-1.0
Keywords: spdx,licenses,database
Platform: UNKNOWN
Classifier: Development Status :: 5 - Production/Stable
Classifier: License :: CC0 1.0 Universal (CC0 1.0) Public Domain Dedication
Classifier: Programming Language :: Python :: 2
Classifier: Programming Language :: Python :: 2.6
Classifier: Programming Language :: Python :: 2.7
Classifier: Programming Language :: Python :: 3
Classifier: Programming Language :: Python :: 3.2
Classifier: Programming Language :: Python :: 3.3
Classifier: Programming Language :: Python :: 3.4
Classifier: Programming Language :: Python :: 3.5
